<?xml version="1.0" encoding="UTF-8"?><?workdir /C:\Drop3and4\Drop4\temp\pdf\oxygen_dita_temp?><?workdir-uri file:/C:/Drop3and4/Drop4/temp/pdf/oxygen_dita_temp/?><?path2project?><?path2project-uri ./?><task-wr xmlns:ditaarch="http://dita.oasis-open.org/architecture/2005/" id="jow1440527541028" xml:lang="en-us" ditaarch:DITAArchVersion="1.2" domains="(topic task task-wr)                            (topic hi-d)                             (topic pr-d)                             (topic sw-d)                            (topic ui-d)                            (topic wr-sw-d)                            (topic xml-d)   " class="- topic/topic task/task task-wr/task-wr ">
<!-- Modification History
        
-->
    <title ixia_locid="1" class="- topic/title ">Changing the Hyper-threading Status</title>
    <shortdesc ixia_locid="2" class="- topic/shortdesc ">The hyper-threading status is controlled by the BIOS settings of the
        host. </shortdesc>
    <prolog class="- topic/prolog ">
        <author ixia_locid="3" class="- topic/author ">Jim Owens</author>
    </prolog>
    <taskbody class="- topic/body task/taskbody ">
        <steps id="steps_v2v_cv3_dt" class="- topic/ol task/steps ">
            <step id="step_N10023_N1001F_N1001C_N10001" ixia_locid="4" class="- topic/li task/step " conref="jow1404333506827.xml#jow1404333506827/lock-node">
                <cmd ixia_locid="5" class="- topic/ph task/cmd "/>
            </step>
            <step id="step_N1002C_N1001F_N1001C_N10001" ixia_locid="6" class="- topic/li task/step ">
                <cmd ixia_locid="7" class="- topic/ph task/cmd ">Edit the host BIOS settings to enable or disable
                    hyper-threading.</cmd>
                <info ixia_locid="8" class="- topic/itemgroup task/info ">
                    <p ixia_locid="9" class="- topic/p ">For more about editing the BIOS, refer to the documentation provided by the
                        maker of the host computer. </p>
                </info>
            </step>
            <step id="step_N1003D_N1001F_N1001C_N10001" ixia_locid="10" class="- topic/li task/step " conref="jow1404333506827.xml#jow1404333506827/unlock-node">
                <cmd ixia_locid="11" class="- topic/ph task/cmd "/>
            </step>
            <step id="step_N10046_N1001F_N1001C_N10001" ixia_locid="12" class="- topic/li task/step ">
                <cmd ixia_locid="13" class="- topic/ph task/cmd ">Confirm the hyper-threading status in HP Helion OpenStack Carrier Grade.</cmd>
                <info ixia_locid="14" class="- topic/itemgroup task/info ">
                    <p ixia_locid="15" class="- topic/p ">The hyper-threading status is reported on the <uicontrol ixia_locid="16" class="+ topic/ph ui-d/uicontrol ">Processor</uicontrol> tab for the host. For more
                        information, see <xref href="jow1404333768530.xml" ixia_locid="17" class="- topic/xref "/>.</p>
                </info>
            </step>
        </steps>
    </taskbody>
</task-wr>